alexfitter/GUI.ipynb
alexfitter/GUI_tess_transit_search.ipynb
alexfitter/__init__.py
alexfitter/basement.py
alexfitter/computer.py
alexfitter/config.py
alexfitter/deriver.py
alexfitter/general_output.py
alexfitter/inout.py
alexfitter/lightcurves.py
alexfitter/mcmc.py
alexfitter/mcmc_output.py
alexfitter/nested_sampling.py
alexfitter/nested_sampling_output.py
alexfitter/observables.py
alexfitter/plot_top_down_view.py
alexfitter/plotting.py
alexfitter/prepare_ttv_fit.py
alexfitter/spots.py
alexfitter/statistics.py
alexfitter/time_series.py
alexfitter/_static/_logos/logo_circ.png
alexfitter/_static/_logos/logo_circ_tess_transit_search.png
alexfitter/_static/_stars/Peacut_Mamajek.csv
alexfitter/_static/_tess/old.csv
alexfitter/_static/_tess/old2.csv
alexfitter/_static/_tess/tess_orbit_times.csv
alexfitter/detection/__init__.py
alexfitter/detection/example.py
alexfitter/detection/injection_recovery.py
alexfitter/detection/injection_recovery_output.py
alexfitter/detection/periodicity.py
alexfitter/detection/transit_search.py
alexfitter/exoworlds_rdx/__init__.py
alexfitter/exoworlds_rdx/lightcurves/__init__.py
alexfitter/exoworlds_rdx/lightcurves/binning.py
alexfitter/exoworlds_rdx/lightcurves/conversions.py
alexfitter/exoworlds_rdx/lightcurves/expand_flags.py
alexfitter/exoworlds_rdx/lightcurves/gp_decor.py
alexfitter/exoworlds_rdx/lightcurves/index_transits.py
alexfitter/exoworlds_rdx/lightcurves/lightcurve_tools.py
alexfitter/exoworlds_rdx/lightcurves/utils.py
alexfitter/exoworlds_rdx/rvs/__init__.py
alexfitter/exoworlds_rdx/rvs/estimate_jitter.py
alexfitter/flares/__init__.py
alexfitter/flares/aflare.py
alexfitter/limb_darkening/LDC3.py
alexfitter/postprocessing/__init__.py
alexfitter/postprocessing/nested_sampling_compare_logZ.py
alexfitter/postprocessing/plot_histograms.py
alexfitter/postprocessing/plot_viol.py
alexfitter/postprocessing/plot_violins.py
alexfitter/priors/__init__.py
alexfitter/priors/estimate_noise.py
alexfitter/priors/estimate_noise_wrap.py
alexfitter-1.2.19.dist-info/LICENSE.txt
alexfitter-1.2.19.dist-info/METADATA
alexfitter-1.2.19.dist-info/WHEEL
alexfitter-1.2.19.dist-info/top_level.txt
alexfitter-1.2.19.dist-info/RECORD
